LICENSE
MANIFEST.in
README.md
requirements.txt
setup.py
tensornet/__init__.py
tensornet/data/__init__.py
tensornet/data/processing.py
tensornet/data/utils.py
tensornet/data/datasets/__init__.py
tensornet/data/datasets/cifar10.py
tensornet/data/datasets/cifar100.py
tensornet/data/datasets/dataset.py
tensornet/data/datasets/mnist.py
tensornet/data/datasets/modest_museum.py
tensornet/data/datasets/tinyimagenet.py
tensornet/engine/__init__.py
tensornet/engine/learner.py
tensornet/engine/lr_finder.py
tensornet/engine/ops/__init__.py
tensornet/engine/ops/checkpoint.py
tensornet/engine/ops/lr_scheduler.py
tensornet/engine/ops/regularizer.py
tensornet/engine/ops/tensorboard.py
tensornet/gradcam/__init__.py
tensornet/gradcam/gradcam.py
tensornet/gradcam/gradcam_pp.py
tensornet/gradcam/visual.py
tensornet/models/__init__.py
tensornet/models/base_model.py
tensornet/models/dsresnet.py
tensornet/models/mobilenetv2.py
tensornet/models/resnet.py
tensornet/models/shufflenetv2.py
tensornet/models/squeezenet.py
tensornet/models/loss/__init__.py
tensornet/models/loss/dice.py
tensornet/models/loss/rmse.py
tensornet/models/loss/ssim.py
tensornet/models/optimizer/__init__.py
tensornet/models/utils/__init__.py
tensornet/models/utils/_utils.py
tensornet/models/utils/summary.py
tensornet/utils/__init__.py
tensornet/utils/cuda.py
tensornet/utils/display.py
tensornet/utils/predictions.py
tensornet/utils/progress_bar.py
torch_tensornet.egg-info/PKG-INFO
torch_tensornet.egg-info/SOURCES.txt
torch_tensornet.egg-info/dependency_links.txt
torch_tensornet.egg-info/requires.txt
torch_tensornet.egg-info/top_level.txt