Metadata-Version: 2.1
Name: torch-tensornet
Version: 1.3.3
Summary: A high-level deep learning library build on top of PyTorch.
Home-page: https://github.com/shan18/TensorNet
Author: Shantanu Acharya
Author-email: thegeek.004@gmail.com
License: MIT
Platform: UNKNOWN
Classifier: Programming Language :: Python :: 3
Classifier: License :: OSI Approved :: MIT License
Classifier: Operating System :: OS Independent
Requires-Python: >=3.6
License-File: LICENSE
